{
    "title": "CHAPTER 1. Trial Jury Selection and Management Act [190 - 242]",
    "path": [
        "CHAPTER 1. Trial Jury Selection and Management Act [190 - 242]"
    ],
    "source_url": "https://leginfo.legislature.ca.gov/faces/codes_displayText.xhtml?lawCode=CCP&division=&title=3.&part=1.&chapter=1.&article=",
    "rule": {
        "rule_id": "191",
        "text": "191. The Legislature recognizes that trial by jury is a cherished constitutional right, and that jury service is an obligation of citizenship.It is the policy of the State of California that all persons selected for jury service shall be selected at random from the population of the area served by the court; that all qualified persons have an equal opportunity, in accordance with this chapter, to be considered for jury service in the state and an obligation to serve as jurors when summoned for that purpose; and that it is the responsibility of jury commissioners to manage all jury systems in an efficient, equitable, and cost-effective manner, in accordance with this chapter.(Repealed and added by Stats. 1988, Ch. 1245, Sec.",
        "metadata": {
            "tags": [
                "service"
            ],
            "subsections": {}
        },
        "last_updated": "N/A"
    }
}